openbuckets/__init__.py
openbuckets/api_client.py
openbuckets/api_response.py
openbuckets/configuration.py
openbuckets/exceptions.py
openbuckets/py.typed
openbuckets/rest.py
openbuckets/api/__init__.py
openbuckets/api/buckets_api.py
openbuckets/api/files_api.py
openbuckets/models/__init__.py
openbuckets/models/bucket.py
openbuckets/models/bucket_search_results.py
openbuckets/models/bucket_search_results_buckets_inner.py
openbuckets/models/bucket_search_results_meta.py
openbuckets/models/bucket_search_results_query.py
openbuckets/models/file.py
openbuckets/models/file_search_results.py
openbuckets/models/file_search_results_files_inner.py
openbuckets/models/file_search_results_meta.py
openbuckets/models/file_search_results_query.py
openbuckets-1.0.4.dist-info/LICENSE
openbuckets-1.0.4.dist-info/METADATA
openbuckets-1.0.4.dist-info/WHEEL
openbuckets-1.0.4.dist-info/top_level.txt
openbuckets-1.0.4.dist-info/RECORD
